[{"number":"T01","distance":0.0,"nameEn":"unknown","nameKr":"나카노","nameJp":"中野"},{"number":"T02","distance":2.0,"nameEn":"unknown","nameKr":"오치아이","nameJp":"落合"},{"number":"T03","distance":3.9,"nameEn":"unknown","nameKr":"다카다노바바","nameJp":"高田馬場"},{"number":"T04","distance":5.6,"nameEn":"unknown","nameKr":"와세다","nameJp":"早稲田"},{"number":"T05","distance":6.8,"nameEn":"unknown","nameKr":"가구라자카","nameJp":"神楽坂"},{"number":"T06","distance":8.0,"nameEn":"unknown","nameKr":"이다바시","nameJp":"飯田橋"},{"number":"T07","distance":8.7,"nameEn":"unknown","nameKr":"구단시타","nameJp":"九段下"},{"number":"T08","distance":9.7,"nameEn":"unknown","nameKr":"다케바시","nameJp":"竹橋"},{"number":"T09","distance":10.7,"nameEn":"unknown","nameKr":"오테마치","nameJp":"大手町"},{"number":"T10","distance":11.5,"nameEn":"unknown","nameKr":"니혼바시","nameJp":"日本橋"},{"number":"T11","distance":12.0,"nameEn":"unknown","nameKr":"가야바초","nameJp":"茅場町"},{"number":"T12","distance":13.8,"nameEn":"unknown","nameKr":"몬젠나카초","nameJp":"門前仲町"},{"number":"T13","distance":14.9,"nameEn":"unknown","nameKr":"기바","nameJp":"木場"},{"number":"T14","distance":15.8,"nameEn":"unknown","nameKr":"도요초","nameJp":"東陽町"},{"number":"T15","distance":17.0,"nameEn":"unknown","nameKr":"미나미스나마치","nameJp":"南砂町"},{"number":"T16","distance":19.7,"nameEn":"unknown","nameKr":"니시카사이","nameJp":"西葛西"},{"number":"T17","distance":20.9,"nameEn":"unknown","nameKr":"가사이","nameJp":"葛西"},{"number":"T18","distance":22.8,"nameEn":"unknown","nameKr":"우라야스","nameJp":"浦安"},{"number":"T19","distance":24.0,"nameEn":"unknown","nameKr":"미나미교토쿠","nameJp":"南行徳"},{"number":"T20","distance":25.5,"nameEn":"unknown","nameKr":"교토쿠","nameJp":"行徳"},{"number":"T21","distance":26.8,"nameEn":"unknown","nameKr":"묘덴","nameJp":"妙典"},{"number":"T22","distance":28.9,"nameEn":"unknown","nameKr":"바라키나카야마","nameJp":"原木中山"},{"number":"T23","distance":30.8,"nameEn":"unknown","nameKr":"니시후나바시","nameJp":"西船橋"}]